simples/__init__.py
simples/soma.py
tests/__init__.py
tests/test_soma.py
simples-0.1.0a0.dist-info/LICENSE
simples-0.1.0a0.dist-info/METADATA
simples-0.1.0a0.dist-info/WHEEL
simples-0.1.0a0.dist-info/top_level.txt
simples-0.1.0a0.dist-info/RECORD
