Metadata-Version: 2.1
Name: simples
Version: 0.1.0a0
Summary: Soma dois números.
Home-page: https://github.com/jecamanga/simples
Author: jeca
Author-email: nyanvamp@gmail.com
License: MIT
Platform: UNKNOWN
Classifier: License :: OSI Approved :: MIT License
Classifier: Programming Language :: Python
Classifier: Programming Language :: Python :: 2
Classifier: Programming Language :: Python :: 3
